{
  "@context": "semantic/context.json",
  "@id": "q:Qa1e06e45-3fd5-4f25-af1e-7c744bd9123a",
  "@type": [
    "object",
    "wq:Q1397073"
  ],
  "label": "distance trajet domicile travail",
  "description": "Distance en voiture de mon trajet domicile travail",
  "thematique": "Mobilité",
  "typology": "Google Map",
  "sourceDataController": "Google",
  "support": "indemnité kilométrique",
  "defi": [
    "Maîtriser son budget mobilité"
  ],
  "kind": "Référentiel",
  "information": "",
  "access": "API trajet",
  "portable": ""
}