{
  "@context": "semantic/context.json",
  "@id": "q:Qba87e1d2-32ec-4429-ad68-9d3d3af52f99",
  "@type": [
    "object",
    "wq:Q1397073"
  ],
  "label": "Pratiques jeux vidéos",
  "description": "Nom du jeu joué, nombre d'heures jouées, ...",
  "thematique": "Ados",
  "typology": "loisirs",
  "sourceDataController": "Plateformes d'achats de jeux (Steam), Editeurs de jeux (Epic Game), ... ",
  "support": "Espace personnel du site web/de l'application",
  "defi": [
    "S'évaluer autrement",
    "Se sensibiliser aux usages numériques"
  ],
  "kind": "Personnelle",
  "information": "Jeux joués",
  "access": "",
  "portable": ""
}