{
  "@context": "semantic/context.json",
  "@id": "q:Qc3e66519-df4f-42be-a439-e4b3817f4de9",
  "@type": [
    "object",
    "wq:Q1397073"
  ],
  "label": "Bourses scolaires",
  "description": "Boursier O/N, montant, date de versement, ...",
  "thematique": "Ados",
  "typology": "",
  "sourceDataController": "Académie de Lyon",
  "support": "Portail Scolarité-Services",
  "defi": [
    "Gérer ses demandes administratives, se faciliter le quotidien (parents, enfants, enseignants)"
  ],
  "kind": "Personnelle",
  "information": "",
  "access": "",
  "portable": ""
}