{
  "@context": "semantic/context.json",
  "@id": "q:Qf79ab2b4-d84c-4311-85fb-0b88648d78ec",
  "@type": [
    "object",
    "wq:Q1397073"
  ],
  "label": "caractéristiques véhicule",
  "description": "modèle, marque, puissance, age, immatriculation, ...",
  "thematique": "Mobilité",
  "typology": "Déplacements",
  "sourceDataController": "assureur",
  "support": "",
  "defi": [
    "Maîtriser son budget mobilité"
  ],
  "kind": "Personnelles - caractéristiques",
  "information": "prix de revient kilométrique",
  "access": "art 20?",
  "portable": "portables"
}